pqss/__init__.py
pqss/main.py
pqss/env/__init__.py
pqss/env/env.py
pqss/lex/__init__.py
pqss/lex/constants.py
pqss/lex/exceptions.py
pqss/lex/lexer.py
pqss/lex/token.py
pqss/lex/utils.py
pqss/parse/__init__.py
pqss/parse/parser.py
pqss/parse/ast/__init__.py
pqss/parse/ast/ast.py
pqss/parse/ast/boolean.py
pqss/parse/ast/builtin.py
pqss/parse/ast/color.py
pqss/parse/ast/identifier.py
pqss/parse/ast/include.py
pqss/parse/ast/integer.py
pqss/parse/ast/mixin.py
pqss/parse/ast/rule.py
pqss/parse/ast/ruleset.py
pqss/parse/ast/selector.py
pqss/parse/ast/unit.py
pqss/parse/ast/var.py
pqss/util/__init__.py
pqss/util/char_util.py
pqss/util/tok_util.py
pqss-0.0.8.dist-info/LICENSE
pqss-0.0.8.dist-info/METADATA
pqss-0.0.8.dist-info/WHEEL
pqss-0.0.8.dist-info/top_level.txt
pqss-0.0.8.dist-info/RECORD
