Metadata-Version: 2.1
Name: pqss
Version: 0.0.8
Summary: PQSS is a dynamic language for qss, like scss for css.
Home-page: http://lyt0628.icu/docs/pqss
Download-URL: http://pypi.org//pqss
Author: lyt0628
Author-email: lyt0628 <lyt.0628@qq.com>
License: Apache License
Project-URL: Repository, https://github.com/LYT0628/pqss
Project-URL: Documentation, http://lyt0628.icu/docs/pqss
Project-URL: Issues, https://github.com/LYT0628/SQSS/pqss
Project-URL: Official Website, https://lyt0628.icu/docs/pqss
Keywords: pyqt,qt,pqss
Classifier: Development Status :: 1 - Planning
Classifier: Programming Language :: Python :: 3
Classifier: Operating System :: OS Independent
Classifier: Natural Language :: Chinese (Simplified)
Classifier: Topic :: Utilities
Requires-Python: >=3.8
License-File: LICENSE
